venue.S.HTML
euphoria/___itinerary/book/Vitamin B.S.HTML
euphoria/___itinerary/book/Vitamin K.S.HTML
euphoria/___itinerary/euphoria.S.HTML
euphoria/___license/license.s.HTML
euphoria/___license/list/gpl-3.0-standalone.html
euphoria/___license/list/vegan.s.HTML
euphoria/__dictionary/euphoria_1
euphoria/__init__.py
euphoria/__status/API/API_status.proc.py
euphoria/__status/API/db_API/records.json
euphoria/__status/main/DB/records.json
euphoria/__status/main/status.proc.py
euphoria/__status/monetary/db/records.json
euphoria/__status/monetary/essence.py
euphoria/__status/monetary/monetary_monitors/monetary_status_1.py
euphoria/__status/monetary/monetary_status.proc.py
euphoria/__status/monetary/status.S.HTML
euphoria/_ellipses--/__init__.py
euphoria/_essence/__init__.py
euphoria/_essence/essence.S.HTML
euphoria/_ops/clique/__init__.py
euphoria/_ops/monitor.py
euphoria/_ops/off.py
euphoria/_ops/on.py
euphoria/_ops/status.py
euphoria/clouds/affiliates_Amazon/affiliates.s.HTML
euphoria/clouds/clouds.S.HTML
euphoria/clouds/food_USDA/deliveries/one/__init__.py
euphoria/clouds/food_USDA/deliveries/one/assertions/branded.py
euphoria/clouds/food_USDA/deliveries/one/assertions/foundational.py
euphoria/clouds/food_USDA/deliveries/one/status/API_status_branded_1.py
euphoria/clouds/food_USDA/deliveries/one/status/API_status_foundational_1.py
euphoria/clouds/food_USDA/deliveries/source.py
euphoria/clouds/food_USDA/examples/__init__.py
euphoria/clouds/food_USDA/examples/branded/Gardein_f'sh_2663758.JSON
euphoria/clouds/food_USDA/examples/branded/Gardein_f'sh_2664238.JSON
euphoria/clouds/food_USDA/examples/branded/beet_juice_2412474.JSON
euphoria/clouds/food_USDA/examples/branded/beet_juice_2642759.JSON
euphoria/clouds/food_USDA/examples/branded/impossible_beef_2664238.JSON
euphoria/clouds/food_USDA/examples/branded/problems/impossible_2468423.JSON
euphoria/clouds/food_USDA/examples/branded/problems/problems.r.HTML
euphoria/clouds/food_USDA/examples/branded/vegan_pizza_2672996.JSON
euphoria-1.0.0.dist-info/METADATA
euphoria-1.0.0.dist-info/WHEEL
euphoria-1.0.0.dist-info/entry_points.txt
euphoria-1.0.0.dist-info/RECORD
