Metadata-Version: 2.1
Name: Euphoria
Version: 1.0.0
Summary: Euphoria is the only cross-platform, versatile, and advanced Python package you will ever need!
Author: Aniketh Chavare
Author-email: anikethchavare@outlook.com
License: Apache License 2.0
Project-URL: Homepage, https://pypi.org/project/Euphoria
Project-URL: Repository, https://github.com/anikethchavare/Euphoria
Project-URL: Documentation, https://anikethchavare.gitbook.io/euphoria
Project-URL: Download, https://github.com/anikethchavare/Euphoria/releases
Project-URL: Changelog, https://github.com/anikethchavare/Euphoria/blob/main/CHANGELOG.md
Project-URL: Issues, https://github.com/anikethchavare/Euphoria/issues
Classifier: Development Status :: 5 - Production/Stable
Classifier: License :: OSI Approved :: Apache Software License
Classifier: Natural Language :: English
Classifier: Operating System :: Microsoft :: Windows
Classifier: Operating System :: MacOS
Classifier: Operating System :: POSIX
Classifier: Programming Language :: Python
Classifier: Programming Language :: Python :: 2
Classifier: Programming Language :: Python :: 3
Classifier: Topic :: Software Development
License-File: LICENSE.txt
Requires-Dist: requests
Requires-Dist: beautifulsoup4
Requires-Dist: colorama
Requires-Dist: pyperclip
Requires-Dist: PyAutoGUI
